{
  "source": "Yahoo Finance",
  "current": 17.4,
  "change": null,
  "change_pct": null,
  "history": [
    {
      "timestamp": "2026-05-05 17:00",
      "value": 17.41
    },
    {
      "timestamp": "2026-05-05 17:01",
      "value": 17.39
    },
    {
      "timestamp": "2026-05-05 17:02",
      "value": 17.4
    },
    {
      "timestamp": "2026-05-05 17:03",
      "value": 17.38
    },
    {
      "timestamp": "2026-05-05 17:04",
      "value": 17.38
    },
    {
      "timestamp": "2026-05-05 17:05",
      "value": 17.39
    },
    {
      "timestamp": "2026-05-05 17:06",
      "value": 17.39
    },
    {
      "timestamp": "2026-05-05 17:07",
      "value": 17.4
    },
    {
      "timestamp": "2026-05-05 17:08",
      "value": null
    },
    {
      "timestamp": "2026-05-05 17:08",
      "value": 17.4
    }
  ],
  "fetch_time": "2026-05-05 17:23:02",
  "fear_level": "较低",
  "fear_description": "市场情绪较为乐观",
  "fear_color": "#8BC34A"
}